datacanvas/__init__.py
datacanvas/dcutils.py
datacanvas/utils.py
dcutils/__init__.py
dcutils/__version__.py
dcutils/core.py
dcPyUtils-0.1.4.dist-info/LICENSE
dcPyUtils-0.1.4.dist-info/METADATA
dcPyUtils-0.1.4.dist-info/WHEEL
dcPyUtils-0.1.4.dist-info/top_level.txt
dcPyUtils-0.1.4.dist-info/RECORD
